dissect/target/__init__.py
dissect/target/container.py
dissect/target/exceptions.py
dissect/target/filesystem.py
dissect/target/loader.py
dissect/target/plugin.py
dissect/target/target.py
dissect/target/volume.py
dissect/target/containers/__init__.py
dissect/target/containers/asdf.py
dissect/target/containers/ewf.py
dissect/target/containers/fortifw.py
dissect/target/containers/hdd.py
dissect/target/containers/hds.py
dissect/target/containers/qcow2.py
dissect/target/containers/raw.py
dissect/target/containers/split.py
dissect/target/containers/vdi.py
dissect/target/containers/vhd.py
dissect/target/containers/vhdx.py
dissect/target/containers/vmdk.py
dissect/target/data/autocompletion/target_bash_completion.sh
dissect/target/filesystems/__init__.py
dissect/target/filesystems/ad1.py
dissect/target/filesystems/btrfs.py
dissect/target/filesystems/cb.py
dissect/target/filesystems/config.py
dissect/target/filesystems/cpio.py
dissect/target/filesystems/dir.py
dissect/target/filesystems/exfat.py
dissect/target/filesystems/extfs.py
dissect/target/filesystems/fat.py
dissect/target/filesystems/ffs.py
dissect/target/filesystems/itunes.py
dissect/target/filesystems/jffs.py
dissect/target/filesystems/nfs.py
dissect/target/filesystems/ntfs.py
dissect/target/filesystems/overlay.py
dissect/target/filesystems/qnxfs.py
dissect/target/filesystems/smb.py
dissect/target/filesystems/squashfs.py
dissect/target/filesystems/tar.py
dissect/target/filesystems/vbk.py
dissect/target/filesystems/vmfs.py
dissect/target/filesystems/vmtar.py
dissect/target/filesystems/xfs.py
dissect/target/filesystems/zip.py
dissect/target/helpers/__init__.py
dissect/target/helpers/cache.py
dissect/target/helpers/config.py
dissect/target/helpers/configutil.py
dissect/target/helpers/cyber.py
dissect/target/helpers/descriptor_extensions.py
dissect/target/helpers/docs.py
dissect/target/helpers/fsutil.py
dissect/target/helpers/hashutil.py
dissect/target/helpers/keychain.py
dissect/target/helpers/lazy.py
dissect_target-3.23.1.dist-info/licenses/COPYRIGHT
dissect_target-3.23.1.dist-info/licenses/LICENSE
dissect_target-3.23.1.dist-info/METADATA
dissect_target-3.23.1.dist-info/WHEEL
dissect_target-3.23.1.dist-info/entry_points.txt
dissect_target-3.23.1.dist-info/top_level.txt
dissect_target-3.23.1.dist-info/RECORD
