Metadata-Version: 2.4
Name: dissect.target
Version: 3.23.1
Summary: This module ties all other Dissect modules together, it provides a programming API and command line tools which allow easy access to various data sources inside disk images or file collections (a.k.a. targets)
Author-email: Dissect Team <dissect@fox-it.com>
License: Affero General Public License v3
Project-URL: homepage, https://dissect.tools
Project-URL: documentation, https://docs.dissect.tools/en/latest/projects/dissect.target
Project-URL: repository, https://github.com/fox-it/dissect.target
Classifier: Development Status :: 5 - Production/Stable
Classifier: Environment :: Console
Classifier: Intended Audience :: Developers
Classifier: Intended Audience :: Information Technology
Classifier: License :: OSI Approved
Classifier: Operating System :: OS Independent
Classifier: Programming Language :: Python :: 3
Classifier: Topic :: Internet :: Log Analysis
Classifier: Topic :: Scientific/Engineering :: Information Analysis
Classifier: Topic :: Security
Classifier: Topic :: Utilities
Requires-Python: ~=3.9
License-File: LICENSE
License-File: COPYRIGHT
Requires-Dist: defusedxml
Requires-Dist: dissect.cstruct<5,>=4
Requires-Dist: dissect.eventlog<4,>=3
Requires-Dist: dissect.evidence<4,>=3
Requires-Dist: dissect.hypervisor<4,>=3.19
Requires-Dist: dissect.ntfs<4,>=3.4
Requires-Dist: dissect.regf<4,>=3.13
Requires-Dist: dissect.sql<4,>=3.12
Requires-Dist: dissect.util<4,>=3
Requires-Dist: dissect.volume<4,>=2
Requires-Dist: flow.record~=3.19.0
Requires-Dist: structlog
Provides-Extra: full
Requires-Dist: asn1crypto; extra == "full"
Requires-Dist: dissect.archive<2,>=1; extra == "full"
Requires-Dist: dissect.btrfs<2,>=1; extra == "full"
Requires-Dist: dissect.cim<4,>=3; extra == "full"
Requires-Dist: dissect.clfs<2,>=1; extra == "full"
Requires-Dist: dissect.esedb<4,>=3; extra == "full"
Requires-Dist: dissect.etl<4,>=3; extra == "full"
Requires-Dist: dissect.extfs<4,>=3; extra == "full"
Requires-Dist: dissect.fat<4,>=3; extra == "full"
Requires-Dist: dissect.ffs<4,>=3; extra == "full"
Requires-Dist: dissect.fve<5,>=4.2; (platform_system != "Windows" or platform_python_implementation != "PyPy") and extra == "full"
Requires-Dist: dissect.jffs<2,>=1.5; extra == "full"
Requires-Dist: dissect.ole<4,>=3; extra == "full"
Requires-Dist: dissect.qnxfs<2,>=1.1; extra == "full"
Requires-Dist: dissect.shellitem<4,>=3; extra == "full"
Requires-Dist: dissect.squashfs<2,>=1; extra == "full"
Requires-Dist: dissect.thumbcache<2,>=1; extra == "full"
Requires-Dist: dissect.vmfs<4,>=3.12; extra == "full"
Requires-Dist: dissect.xfs<4,>=3; extra == "full"
Requires-Dist: ipython; extra == "full"
Requires-Dist: fusepy; extra == "full"
Requires-Dist: pycryptodome; extra == "full"
Requires-Dist: ruamel.yaml; extra == "full"
Requires-Dist: tomli; python_version < "3.11" and extra == "full"
Requires-Dist: zstandard==0.23.0; (platform_python_implementation == "PyPy" and python_version == "3.9") and extra == "full"
Requires-Dist: zstandard; (platform_python_implementation != "PyPy" and python_version != "3.9") and extra == "full"
Provides-Extra: dev
Requires-Dist: dissect.target[full,yara]; extra == "dev"
Requires-Dist: dissect.archive[dev]<2.0.dev,>=1.0.dev; extra == "dev"
Requires-Dist: dissect.btrfs[dev]<2.0.dev,>=1.0.dev; extra == "dev"
Requires-Dist: dissect.cim[dev]<4.0.dev,>=3.0.dev; extra == "dev"
Requires-Dist: dissect.clfs[dev]<2.0.dev,>=1.0.dev; extra == "dev"
Requires-Dist: dissect.cstruct<5.0.dev,>=4.0.dev; extra == "dev"
Requires-Dist: dissect.esedb[dev]<4.0.dev,>=3.0.dev; extra == "dev"
Requires-Dist: dissect.etl[dev]<4.0.dev,>=3.0.dev; extra == "dev"
Requires-Dist: dissect.eventlog[dev]<4.0.dev,>=3.0.dev; extra == "dev"
Requires-Dist: dissect.evidence[dev]<4.0.dev,>=3.0.dev; extra == "dev"
Requires-Dist: dissect.extfs[dev]<4.0.dev,>=3.0.dev; extra == "dev"
Requires-Dist: dissect.fat[dev]<4.0.dev,>=3.0.dev; extra == "dev"
Requires-Dist: dissect.ffs[dev]<4.0.dev,>=3.0.dev; extra == "dev"
Requires-Dist: dissect.fve[dev]<5.0.dev,>=4.2.dev; (platform_system != "Windows" or platform_python_implementation != "PyPy") and extra == "dev"
Requires-Dist: dissect.hypervisor[dev]<4.0.dev,>=3.19.dev; extra == "dev"
Requires-Dist: dissect.jffs[dev]<2.0.dev,>=1.5.dev; extra == "dev"
Requires-Dist: dissect.ntfs[dev]<4.0.dev,>=3.4.dev; extra == "dev"
Requires-Dist: dissect.qnxfs[dev]<2.0.dev,>=1.1.dev; extra == "dev"
Requires-Dist: dissect.regf[dev]<4.0.dev,>=3.13.dev; extra == "dev"
Requires-Dist: dissect.shellitem[dev]<4.0.dev,>=3.0.dev; extra == "dev"
Requires-Dist: dissect.sql[dev]<4.0.dev,>=3.12.dev; extra == "dev"
Requires-Dist: dissect.squashfs[dev]<2.0.dev,>=1.0.dev; extra == "dev"
Requires-Dist: dissect.thumbcache[dev]<2.0.dev,>=1.0.dev; extra == "dev"
Requires-Dist: dissect.util<4.0.dev,>=3.0.dev; extra == "dev"
Requires-Dist: dissect.vmfs[dev]<4.0.dev,>=3.12.dev; extra == "dev"
Requires-Dist: dissect.volume[dev]<4.0.dev,>=3.0.dev; extra == "dev"
Requires-Dist: dissect.xfs[dev]<4.0.dev,>=3.0.dev; extra == "dev"
Requires-Dist: pexpect; extra == "dev"
Requires-Dist: docutils; extra == "dev"
Requires-Dist: typing_extensions; extra == "dev"
Provides-Extra: yara
Requires-Dist: dissect.target[full]; extra == "yara"
Requires-Dist: yara-python>=4.3.0; extra == "yara"
Provides-Extra: smb
Requires-Dist: dissect.target[full]; extra == "smb"
Requires-Dist: impacket==0.10.0; extra == "smb"
Provides-Extra: cb
Requires-Dist: dissect.target[full]; extra == "cb"
Requires-Dist: carbon-black-cloud-sdk~=1.4.3; extra == "cb"
Provides-Extra: mqtt
Requires-Dist: dissect.target[full]; extra == "mqtt"
Requires-Dist: paho-mqtt==1.6.1; extra == "mqtt"
Dynamic: license-file
